fguard/__init__.py
fguard/cli.py
fguard/core/__init__.py
fguard/core/communication.py
fguard/core/handler.py
fguard/core/utils.py
fguard/core/vision.py
fguard/core/unet/__init__.py
fguard/core/unet/unet_model.py
fguard/core/unet/unet_parts.py
fguard-1.2.0.dist-info/LICENSE
fguard-1.2.0.dist-info/METADATA
fguard-1.2.0.dist-info/WHEEL
fguard-1.2.0.dist-info/entry_points.txt
fguard-1.2.0.dist-info/top_level.txt
fguard-1.2.0.dist-info/RECORD
