Metadata-Version: 2.1
Name: fguard
Version: 1.2.0
Summary: Detect deforestation on area over a given period of time
Home-page: https://forestguardian.ru/
Author: Ivan Gronsky
License: GPL-3.0
Classifier: Development Status :: 4 - Beta
Classifier: Programming Language :: Python :: 3
Classifier: License :: OSI Approved :: GNU General Public License v3 (GPLv3)
Classifier: Operating System :: OS Independent
Requires-Python: >=3.8
License-File: LICENSE
Requires-Dist: click ==8.1.7
Requires-Dist: eo-learn ==1.5.2
Requires-Dist: joblib ==1.3.2
Requires-Dist: numpy ==1.26.3
Requires-Dist: onnxruntime ==1.18.0
Requires-Dist: opencv-python ==4.8.1.78
Requires-Dist: platformdirs ==4.2.1
Requires-Dist: python-dotenv ==1.0.0
Requires-Dist: requests ==2.31.0
Requires-Dist: tqdm ==4.66.2
